modelx_cython/__init__.py
modelx_cython/__main__.py
modelx_cython/_mx_sys.pxd
modelx_cython/builder.py
modelx_cython/cli.py
modelx_cython/config.py
modelx_cython/consts.py
modelx_cython/monkeytype_tracing.py
modelx_cython/parser.py
modelx_cython/tracer.py
modelx_cython/transformer.py
modelx_cython/typedefs.py
modelx_cython-0.0.8.dist-info/licenses/LICENSE.GPL.txt
modelx_cython-0.0.8.dist-info/licenses/LICENSE.txt
modelx_cython-0.0.8.dist-info/METADATA
modelx_cython-0.0.8.dist-info/WHEEL
modelx_cython-0.0.8.dist-info/entry_points.txt
modelx_cython-0.0.8.dist-info/top_level.txt
modelx_cython-0.0.8.dist-info/RECORD
