Metadata-Version: 2.4
Name: modelx-cython
Version: 0.0.8
Summary: Cythonize modelx models.
Author-email: Fumito Hamamura <fumito.ham@gmail.com>
License: LGPLv3
Project-URL: Homepage, https://modelx.io
Project-URL: Documentation, https://docs.modelx.io
Project-URL: Repository, https://github.com/fumitoh/modelx-cython.git
Keywords: finance,quants,actuary
Classifier: Development Status :: 3 - Alpha
Classifier: Intended Audience :: Financial and Insurance Industry
Classifier: Intended Audience :: Science/Research
Classifier: Topic :: Office/Business :: Financial
Classifier: Topic :: Office/Business :: Financial :: Accounting
Classifier: Topic :: Office/Business :: Financial :: Investment
Classifier: Topic :: Office/Business :: Financial :: Spreadsheet
Classifier: Topic :: Scientific/Engineering :: Mathematics
Classifier: License :: OSI Approved :: GNU Lesser General Public License v3 (LGPLv3)
Classifier: Operating System :: OS Independent
Classifier: Programming Language :: Python :: 3
Classifier: Programming Language :: Python :: 3.7
Classifier: Programming Language :: Python :: 3.8
Classifier: Programming Language :: Python :: 3.9
Classifier: Programming Language :: Python :: 3.10
Classifier: Programming Language :: Python :: 3.11
Requires-Python: >=3.7
License-File: LICENSE.GPL.txt
License-File: LICENSE.txt
Requires-Dist: modelx
Requires-Dist: libcst
Requires-Dist: Cython
Requires-Dist: setuptools
Requires-Dist: MonkeyType
Requires-Dist: numpy
Dynamic: license-file
